MANIFEST.in
README.txt
setup.cfg
setup.py
src/requires.txt
src/m3_task_scheduler/__init__.py
src/m3_task_scheduler/api.py
src/m3_task_scheduler/models.py
src/m3_task_scheduler/tests.py
src/m3_task_scheduler/version.py
src/m3_task_scheduler.egg-info/PKG-INFO
src/m3_task_scheduler.egg-info/SOURCES.txt
src/m3_task_scheduler.egg-info/dependency_links.txt
src/m3_task_scheduler.egg-info/top_level.txt
src/m3_task_scheduler/management/__init__.py
src/m3_task_scheduler/management/commands/__init__.py
src/m3_task_scheduler/management/commands/execute_tasks.py
src/m3_task_scheduler/migrations/0001_initial.py
src/m3_task_scheduler/migrations/__init__.py
src/tests/__init__.py
src/tests/manage.py
src/tests/prepare_env.py
src/tests/settings.py
src/tests/shell.sh
src/tests/test.sh
src/tests/urls.py
src/tests/version.py
src/tests/core/__init__.py
src/tests/core/tests.py