Metadata-Version: 1.1
Name: m3-task-scheduler
Version: 1.0
Summary: Планировщик
Home-page: UNKNOWN
Author: BARS Group
Author-email: bars@bars-open.ru
License: MIT
Platform: UNKNOWN
Classifier: Intended Audience :: Developers
Classifier: Environment :: Web Environment
Classifier: Natural Language :: Russian
Classifier: Natural Language :: English
Classifier: Operating System :: OS Independent
Classifier: Programming Language :: Python
Classifier: License :: OSI Approved :: MIT License
Classifier: Development Status :: 5 - Production/Stable
